clase/__init__.py
clase/functions.py
EDA_NA-1.0.dist-info/METADATA
EDA_NA-1.0.dist-info/WHEEL
EDA_NA-1.0.dist-info/top_level.txt
EDA_NA-1.0.dist-info/RECORD
